{"front_guide_lib.md":"194f8eff","front_dep_icon.md":"55ad0a58","front_components_icon.md":"45053342","back_guide_index.md":"554f4a63","front_guide_component.md":"5531b1ef","index.md":"fd0467a1","frame_auth.md":"f3d0d400","version_v1.0.0.md":"94b74650","frame_index.md":"d71f628f","back_guide_instruction.md":"f816eaf1","back_guide_deploy.md":"7d7c80aa","front_guide_introduction.md":"87b7207f","back_guide_introduction.md":"4f07220c","front_dep_i18n.md":"bafd8ea2","front_guide_auth.md":"cc7f0d46","front_dep_cors.md":"b894c855","version_v1.1.0.md":"7e8a09de","front_guide_index.md":"24486626","front_guide_menu.md":"54e6fedc","back_guide_generation.md":"741bec30","front_guide_deploy.md":"48a97f8d","front_dep_dark.md":"97516b84","back_guide_settings.md":"5c393b32","frame_introduction.md":"9aa865b6","front_guide_mock.md":"d1200956","front_guide_design.md":"a2d37153","front_guide_router.md":"e939c7e2","front_guide_settings.md":"881d81bd"}
